RPyCRobotRemote/RPyCRobotRemoteClient.py
RPyCRobotRemote/RPyCRobotRemoteServer.py
RPyCRobotRemote/__init__.py
RPyCRobotRemote/_version.py
robotframework_rpycremote-0.0.18.dist-info/LICENSE.txt
robotframework_rpycremote-0.0.18.dist-info/METADATA
robotframework_rpycremote-0.0.18.dist-info/WHEEL
robotframework_rpycremote-0.0.18.dist-info/top_level.txt
robotframework_rpycremote-0.0.18.dist-info/RECORD
